Workbook
Name IQ_CH: 110000
Name IQ_CQ: 5000
Name IQ_CY: 10000
Name IQ_DAILY: 500000
Name IQ_FH: 100000
Name IQ_FQ: 500
Name IQ_FY: 1000
Name IQ_LTM: 2000
Name IQ_MONTH: 15000
Name IQ_NTM: 6000
Name IQ_WEEK: 50000
Name IQ_YTD: 3000

Sheet SE
A1: Date | B1: 45596 | C1: 45626 | D1: 45657 | E1: 45688 | F1: 45716 | G1: 45747 | H1: 45777 | I1: 45808 | J1: 45838 | K1: 45869 | L1: 45900 | M1: 45930
O2: Volumes Before | P2: LTM | Q2: L6M | R2: L3M | S2: PHD FM | V2: Volumes After | W2: LTM | X2: L6M | Y2: L3M | Z2: PHD FM
A3: Oil Volume (BBLs) | B3: 72353.848 | C3: 70502.478 | D3: 76291.781 | E3: 70952.101 | F3: 62662.083 | G3: 74883.63 | H3: 74829.498 | I3: 76786.121 | J3: 78039.753 | K3: 69919.451 | L3: 71142.207 | M3: 76706.797 | O3: Oil, Mbbl | P3: =AVERAGE(B3:M3) -> 72922.479 | Q3: =AVERAGE(H3:M3) -> 74570.638 | R3: =AVERAGE(K3:M3) -> 72589.485 | S3: 74.3 | V3: Oil, Mbbl | W3: 72.922479 | X3: 74.570638 | Y3: 72.589485 | Z3: 74.3
A4: Gas Volume (MCF) | B4: 0 | C4: 0 | D4: 0 | E4: 0 | F4: 0 | G4: 0 | H4: 0 | I4: 0 | J4: 0 | K4: 0 | L4: 0 | M4: 0 | O4: Gas, MMcf | P4: =AVERAGE(B4:M4) -> 0 | Q4: =AVERAGE(H4:M4) -> 0 | R4: =AVERAGE(K4:M4) -> 0 | V4: Gas, MMcf | W4: 0 | X4: 0 | Y4: 0
A5: NGL Volume (BBLs) | B5: 9207.996 | C5: 8723.234 | D5: 8649.823 | E5: 7846.271 | F5: 6166.18 | G5: 8340.917 | H5: 8759.578 | I5: 6530.336 | J5: 11455.54 | K5: 2682.949 | L5: 9555.773 | M5: 9242.44 | O5: NGL, Mbbl | P5: =AVERAGE(B5:M5) -> 8096.7531 | Q5: =AVERAGE(H5:M5) -> 8037.7693 | R5: =AVERAGE(K5:M5) -> 7160.3873 | S5: 4.49 | V5: NGL, Mbbl | W5: 8.0967531 | X5: 8.0377693 | Y5: 7.1603873 | Z5: 4.49
A6: Total (Boe) | B6: 81561.844 | C6: 79225.712 | D6: 84941.604 | E6: 78798.372 | F6: 68828.263 | G6: 83224.547 | H6: 83589.076 | I6: 83316.457 | J6: 89495.293 | K6: 72602.4 | L6: 80697.98 | M6: 85949.237
A9: Oil Revenue | B9: 4554938.1 | C9: 4410882.8 | D9: 4784355.5 | E9: 4808684.2 | F9: 4010354.5 | G9: 4443915.3 | H9: 4169707.1 | I9: 4335379.9 | J9: 4928770.3 | K9: 4424675 | L9: 4171704.3 | M9: 4342062.5
A10: Gas Revenue | B10: 0 | C10: 0 | D10: 0 | E10: 0 | F10: 0 | G10: 0 | H10: 0 | I10: 0 | J10: 0 | K10: 0 | L10: 0 | M10: 0
A11: NGL Revenue | B11: 506236.61 | C11: 486197.25 | D11: 466767.59 | E11: 453514.62 | F11: 329502.51 | G11: 431592.81 | H11: 423339.83 | I11: 314637.75 | J11: 543535.02 | K11: 121273.23 | L11: 456105.65 | M11: 438200.52
A12: Sulfur Revenue | B12: 9309.16 | C12: 6987.7 | D12: 7014.08 | E12: 19593.22 | F12: 17115.89 | G12: 15500.24 | H12: 36321.96 | I12: 41681.95 | J12: 46819.6 | K12: 14178.88 | L12: 38142.1 | M12: 37737.15
A13: Midstream Revenue | B13: 0 | C13: 0 | D13: 0 | E13: 0 | F13: 0 | G13: 0 | H13: 0 | I13: 0 | J13: 0 | K13: 0 | L13: 0 | M13: 0
A14: Service Revenue | B14: 0 | C14: 0 | D14: 0 | E14: 0 | F14: 0 | G14: 0 | H14: 0 | I14: 0 | J14: 0 | K14: 0 | L14: 0 | M14: 0
A15: Other Revenue | B15: 0 | C15: 0 | D15: 0 | E15: 0 | F15: 0 | G15: 0 | H15: 0 | I15: 0 | J15: 0 | K15: 0 | L15: 0 | M15: 0
A16: Total Revenue | B16: 5070483.9 | C16: 4904067.8 | D16: 5258137.2 | E16: 5281792 | F16: 4356972.9 | G16: 4891008.3 | H16: 4629368.8 | I16: 4691699.6 | J16: 5519124.9 | K16: 4560127.2 | L16: 4665952 | M16: 4818000.2
A18: Oil Realized Price $/bbl | B18: =B9/B3 -> 62.95364 | C18: =C9/C3 -> 62.563515 | D18: =D9/D3 -> 62.711283 | E18: =E9/E3 -> 67.773669 | F18: =F9/F3 -> 63.9997 | G18: =G9/G3 -> 59.344283 | H18: =H9/H3 -> 55.722772 | I18: =I9/I3 -> 56.460462 | ... M18: =M9/M3 -> 56.605968
A19: Gas Realized Price, $/Mcf
A20: NGL Realized Price, $/bbl | B20: =B11/B5 -> 54.977935 | C20: =C11/C5 -> 55.735895 | D20: =D11/D5 -> 53.962675 | E20: =E11/E5 -> 57.80002 | F20: =F11/F5 -> 53.437057 | G20: =G11/G5 -> 51.744048 | H20: =H11/H5 -> 48.328793 | I20: =I11/I5 -> 48.180944 | ... M20: =M11/M5 -> 47.411779
A22: WTI | B22: 71.99 | C22: 69.95 | D22: 70.12 | E22: 75.74 | F22: 71.53 | G22: 68.24 | H22: 63.54 | I22: 62.17 | J22: 68.17 | K22: 68.39 | L22: 64.86 | M22: 63.96
A23: HH | B23: 2.2 | C23: 2.12 | D23: 3.01 | E23: 4.13 | F23: 4.19 | G23: 4.12 | H23: 3.42 | I23: 3.12 | J23: 3.02 | K23: 3.2 | L23: 2.91 | M23: 2.97
O24: Diffs Before | P24: LTM | Q24: L6M | R24: L3M | S24: PHD FM | V24: Diffs After | W24: LTM | X24: L6M | Y24: L3M | Z24: PHD FM
A25: Oil Differential | B25: =B18-B22 -> -9.0363601 | C25: =C18-C22 -> -7.3864849 | D25: =D18-D22 -> -7.4087167 | E25: =E18-E22 -> -7.9663314 | F25: =F18-F22 -> -7.5303002 | G25: =G18-G22 -> -8.8957174 | H25: =H18-H22 -> -7.8172279 | I25: =I18-I22 -> -5.7095381 | ... M25: =M18-M22 -> -7.3540321 | O25: Oil Differential | P25: =AVERAGE(B25:M25) -> -7.1205102 | Q25: =AVERAGE(H25:M25) -> -6.2037019 | R25: =AVERAGE(K25:M25) -> -6.22754 | S25: -6.92 | V25: Oil Differential | W25: -7.1205102 | X25: -6.2037019 | Y25: -6.22754 | Z25: -7.12
A26: Gas Differential | O26: Gas Differential | V26: Gas Differential
A27: NGL Differential | B27: =B20/B22 -> 0.76368851 | C27: =C20/C22 -> 0.7967962 | D27: =D20/D22 -> 0.76957609 | E27: =E20/E22 -> 0.76313731 | F27: =F20/F22 -> 0.74705797 | G27: =G20/G22 -> 0.75826565 | H27: =H20/H22 -> 0.76060423 | I27: =I20/I22 -> 0.77498703 | ... M27: =M20/M22 -> 0.74127234 | O27: NGL Differential | P27: =AVERAGE(B27:M27) -> 0.74735365 | Q27: =AVERAGE(H27:M27) -> 0.72828701 | R27: =AVERAGE(K27:M27) -> 0.71270523 | S27: 0.75 | V27: NGL Differential | W27: 0.74735365 | X27: 0.72828701 | Y27: 0.71270523 | Z27: 0.75
A30: Midstream Expense | B30: 0 | C30: 0 | D30: 0 | E30: 0 | F30: 0 | G30: 0 | H30: 0 | I30: 0 | J30: 0 | K30: 0 | L30: 0 | M30: 0
A31: Fuel, Electricity, & Utilities | B31: 479.04607 | C31: 510.89774 | D31: 484.76979 | E31: 474.93265 | F31: 194.40062 | G31: 503.0843 | H31: 456.83842 | I31: 478.34714 | J31: 487.82062 | K31: 475.87388 | L31: 495.53346 | M31: 473.0035
A32: Workover | B32: 124.44255 | C32: 132.12848 | D32: 106.23674 | E32: 187.82488 | F32: 127.46457 | G32: 192.66466 | H32: 123.65126 | I32: 173.39351 | J32: 127.41323 | K32: 217.81627 | L32: 116.16436 | M32: 68.35498
A33: CO2 | B33: 0 | C33: 0 | D33: 0 | E33: 0 | F33: 0 | G33: 0 | H33: 0 | I33: 0 | J33: 0 | K33: 0 | L33: 0 | M33: 0
A34: Labor | B34: 198.17684 | C34: 239.55349 | D34: 443.21963 | E34: 226.63097 | F34: 209.50491 | G34: 220.9353 | H34: 238.478 | I34: 200.17804 | J34: 206.03131 | K34: 204.4353 | L34: 202.72731 | M34: 180.19448
A35: Chemicals | B35: 77.10179 | C35: 80.66513 | D35: 27.73811 | E35: 111.40458 | F35: 43.97685 | G35: 109.96171 | H35: 66.67869 | I35: 63.86407 | J35: 80.49385 | K35: 83.48149 | L35: 78.81188 | M35: 83.1645
A36: Materials & Supplies | B36: 44.64617 | C36: 22.85891 | D36: 14.10566 | E36: 13.205175 | F36: 27.93664 | G36: 21.72686 | H36: -10.15652 | I36: 47.42476 | J36: 15.27895 | K36: 32.04288 | L36: 9.70552 | M36: 12.34242
A37: Services | B37: 54.66784 | C37: 27.4924 | D37: 36.41588 | E37: 45.0126 | F37: 36.764 | G37: 36.4145 | H37: 39.77469 | I37: 48.80124 | J37: 38.77068 | K37: 27.521 | L37: 34.83635 | M37: 27.2012
A38: EHS, Land, Legal, & Regulatory | B38: 8.3018 | C38: 11.90457 | D38: 22.63644 | E38: 11.28643 | F38: 5.60932 | G38: 11.9941 | H38: 5.26079 | I38: 8.58166 | J38: 22.89204 | K38: 8.1492 | L38: 9.14616 | M38: 9.93018
A39: Repairs & Maintenance | B39: 6.1806 | C39: 3.4136 | D39: 11.23559 | E39: 3.09176 | F39: 7.26672 | G39: 6.1478 | H39: 2.18051 | I39: 0 | J39: 6.16987 | K39: 6.563 | L39: 3.79658 | M39: 1.90016
A40: Compression | B40: 0 | C40: 0 | D40: 0 | E40: 0 | F40: 0 | G40: 0 | H40: 0 | I40: 0 | J40: 0 | K40: 0 | L40: 0 | M40: 0
A41: Insurance | B41: 21.12828 | C41: 19.61458 | D41: 52.87402 | E41: 38.67281 | F41: 31.13933 | G41: 46.60311 | H41: 36.28612 | I41: 29.60092 | J41: 36.48683 | K41: 22.33732 | L41: 29.95732 | M41: 24.25469
... A49: Accrued Fixed LOE | B49: 0 | C49: 0 | D49: 0 | E49: 0 | F49: 0 | G49: 0 | H49: 0 | I49: 0 | J49: 0 | K49: 0 | L49: 0 | M49: 0
A50: Other | B50: 0.24851 | C50: 0 | D50: 1.80994 | E50: 0 | F50: 0 | G50: 0.063 | H50: 1.195 | I50: 0 | J50: 2.521 | K50: 0.063 | L50: 2.494 | M50: 4.577 | O50: Expenses Before | P50: LTM | Q50: L6M | R50: L3M | V50: Expenses After | W50: LTM | X50: L6M | Y50: L3M
A51: Total Operating Expenses | B51: 1371674.5 | C51: 1364803.3 | D51: 1523362 | E51: 1424978.2 | F51: 980693.2 | G51: 1473889.9 | H51: 1339256.3 | I51: 1438702.6 | J51: 1396490.9 | K51: 1332422.4 | L51: 1356914.8 | M51: 1228031.6 | O51: LOS, M$ | P51: =AVERAGE(B51:M51) -> 1352601.7 | Q51: =AVERAGE(H51:M51) -> 1348636.4 | R51: =AVERAGE(K51:M51) -> 1305789.6 | V51: LOS, M$ | W51: 1352.6017 | X51: 1348.6364 | Y51: 1305.7896
O52: PHD FM, M$ | P52: 1386.64 | Q52: 1386.64 | R52: 1386.64 | V52: PHD FM, M$ | W52: 1386.64 | X52: 1386.64 | Y52: 1386.64
A53: Oil Deducts | B53: 56.13897 | C53: 47.48521 | D53: 50.41295 | E53: 44.44943 | F53: 40.46141 | G53: 45.76795 | H53: 48.08025 | I53: 52.01625 | J53: 60.89818 | K53: 55.34786 | L53: 44.30751 | M53: 43.88248 | O53: Diff, M$ | P53: =P52-P51 -> -1351215 | Q53: =Q52-Q51 -> -1347249.8 | R53: =R52-R51 -> -1304403 | V53: Diff, M$ | W53: 34.038343 | X53: 38.003553 | Y53: 80.850373
A54: Gas Deducts | B54: 0 | C54: 0 | D54: 0 | E54: 0 | F54: 0 | G54: 0 | H54: 0 | I54: 0 | J54: 0 | K54: 0 | L54: 0 | M54: 0 | O54: Diff, % | P54: =P53/P52 -> -974.45265 | Q54: =Q53/Q52 -> -971.59306 | R54: =R53/R52 -> -940.69332 | V54: Diff, % | W54: 0.024547354 | X54: 0.027406936 | Y54: 0.058306679
A55: NGL Deducts | B55: 246.85923 | C55: 235.65905 | D55: 234.10908 | E55: 217.71283 | F55: 198.40691 | G55: 238.23746 | H55: 232.30045 | I55: 235.14647 | J55: 238.0495 | K55: 117.59467 | L55: 261.73174 | M55: 243.09485
A56: Other Transportation | B56: 0 | C56: 0 | D56: 0 | E56: 0 | F56: 0 | G56: 0 | H56: 0 | I56: 0 | J56: 0 | K56: 0 | L56: 0 | M56: 0
A57: Total Deducts | B57: 302.9982 | C57: 283.14426 | D57: 284.52203 | E57: 262.16226 | F57: 238.86832 | G57: 284.00541 | H57: 280.3807 | I57: 287.16272 | J57: 298.94768 | K57: 172.94253 | L57: 306.03925 | M57: 286.97733
A59: Oil Severance Taxes | B59: 489.27513 | C59: 475.1635 | D59: 516.43255 | E59: 518.68991 | F59: 429.11415 | G59: 474.98071 | H59: 444.20955 | I59: 464.42827 | J59: 521.81204 | K59: 473.40564 | L59: 449.3763 | M59: 463.1372
A60: Gas Severance Taxes | B60: 0 | C60: 0 | D60: 0 | E60: 0 | F60: 0 | G60: 0 | H60: 0 | I60: 0 | J60: 0 | K60: 0 | L60: 0 | M60: 0
A61: NGL Severance Taxes | B61: 25.78471 | C61: 23.52382 | D61: 21.98897 | E61: 22.52245 | F61: 12.73836 | G61: 17.38259 | H61: 17.7894 | I61: 7.22012 | J61: 28.54236 | K61: 0.15569 | L61: 17.82225 | M61: 18.09256
A62: Sulfur Severance Taxes | B62: 0.97143 | C62: 0.69264 | D62: 0.70283 | E62: 1.95714 | F62: 1.75876 | G62: 1.48523 | H62: 3.56557 | I62: 4.13604 | J62: 4.5699 | K62: 1.3743 | L62: 3.64202 | M62: 3.64675
A63: Other Severance Taxes | B63: 0 | C63: 0 | D63: 0 | E63: 0 | F63: 0 | G63: 0 | H63: 0 | I63: 0 | J63: 0 | K63: 0 | L63: 0 | M63: 0
A64: Ad Valorem Taxes | B64: 0.10826 | C64: 0 | D64: 0 | E64: 0 | F64: 0 | G64: 0 | H64: 0 | I64: 0 | J64: 0 | K64: 0 | L64: 0 | M64: 0
A65: Total Production Taxes | B65: 516.13953 | C65: 499.37996 | D65: 539.12435 | E65: 543.1695 | F65: 443.61127 | G65: 493.84853 | H65: 465.56452 | I65: 475.78443 | J65: 554.9243 | K65: 474.93563 | L65: 470.84057 | M65: 484.87651 | O65: Taxes Before | P65: LTM | Q65: L6M | R65: L3M | S65: PHD FM | V65: Taxes After | W65: LTM | X65: L6M | Y65: L3M | Z65: PHD FM
A66: Tax as % of Net Rec | B66: =B65/B16 -> 0.00010179295 | C66: =C65/C16 -> 0.00010182974 | D66: =D65/D16 -> 0.00010253144 | E66: =E65/E16 -> 0.00010283811 | F66: =F65/F16 -> 0.00010181639 | G66: =G65/G16 -> 0.0001009707 | H66: =H65/H16 -> 0.0001005676 | I66: =I65/I16 -> 0.00010140982 | ... M66: =M65/M16 -> 0.00010063854 | O66: As % of Net Rev | P66: =AVERAGE(B66:M66) -> 0.00010166671 | Q66: =AVERAGE(H66:M66) -> 0.0001013702 | R66: =AVERAGE(K66:M66) -> 0.00010189935 | S66: =277.65/(2614.66+226.21) -> 0.097734145 | V66: As % of Net Rev | W66: 0.10166671 | X66: 0.1013702 | Y66: 0.10189935 | Z66: 0.097734145

Sheet Sheet2
A1: 4554.9381 | B1: 4410.8828 | C1: 4784.3555 | D1: 4808.6842 | E1: 4010.3545 | F1: 4443.9153 | G1: 4169.7071 | H1: 4335.3799 | I1: 4928.7703 | J1: 4424.675 | K1: 4171.7043 | L1: 4342.0625
A2: 0 | B2: 0 | C2: 0 | D2: 0 | E2: 0 | F2: 0 | G2: 0 | H2: 0 | I2: 0 | J2: 0 | K2: 0 | L2: 0
A3: 506.23661 | B3: 486.19725 | C3: 466.76759 | D3: 453.51462 | E3: 329.50251 | F3: 431.59281 | G3: 423.33983 | H3: 314.63775 | I3: 543.53502 | J3: 121.27323 | K3: 456.10565 | L3: 438.20052
A4: 9.30916 | B4: 6.9877 | C4: 7.01408 | D4: 19.59322 | E4: 17.11589 | F4: 15.50024 | G4: 36.32196 | H4: 41.68195 | I4: 46.8196 | J4: 14.17888 | K4: 38.1421 | L4: 37.73715
A5: =A1*1000 -> 4554938.1 | B5: =B1*1000 -> 4410882.8 | C5: =C1*1000 -> 4784355.5 | D5: =D1*1000 -> 4808684.2 | E5: =E1*1000 -> 4010354.5 | F5: =F1*1000 -> 4443915.3 | G5: =G1*1000 -> 4169707.1 | H5: =H1*1000 -> 4335379.9 | ... L5: =L1*1000 -> 4342062.5
A6: =A2*1000 -> 0 | B6: =B2*1000 -> 0 | C6: =C2*1000 -> 0 | D6: =D2*1000 -> 0 | E6: =E2*1000 -> 0 | F6: =F2*1000 -> 0 | G6: =G2*1000 -> 0 | H6: =H2*1000 -> 0 | ... L6: =L2*1000 -> 0
A7: =A3*1000 -> 506236.61 | B7: =B3*1000 -> 486197.25 | C7: =C3*1000 -> 466767.59 | D7: =D3*1000 -> 453514.62 | E7: =E3*1000 -> 329502.51 | F7: =F3*1000 -> 431592.81 | G7: =G3*1000 -> 423339.83 | H7: =H3*1000 -> 314637.75 | ... L7: =L3*1000 -> 438200.52
A8: =A4*1000 -> 9309.16 | B8: =B4*1000 -> 6987.7 | C8: =C4*1000 -> 7014.08 | D8: =D4*1000 -> 19593.22 | E8: =E4*1000 -> 17115.89 | F8: =F4*1000 -> 15500.24 | G8: =G4*1000 -> 36321.96 | H8: =H4*1000 -> 41681.95 | ... L8: =L4*1000 -> 37737.15

Sheet PowerBI_Long
A1: Date | B1: Category | C1: Line Item | D1: Value
A2: =SE!B$1 -> 45596 | B2: Volumes | C2: Oil Volume (MBBLs) | D2: =SE!B3 -> 72353.848
A3: =SE!C$1 -> 45626 | B3: Volumes | C3: Oil Volume (MBBLs) | D3: =SE!C3 -> 70502.478
A4: =SE!D$1 -> 45657 | B4: Volumes | C4: Oil Volume (MBBLs) | D4: =SE!D3 -> 76291.781
A5: =SE!E$1 -> 45688 | B5: Volumes | C5: Oil Volume (MBBLs) | D5: =SE!E3 -> 70952.101
A6: =SE!F$1 -> 45716 | B6: Volumes | C6: Oil Volume (MBBLs) | D6: =SE!F3 -> 62662.083
A7: =SE!G$1 -> 45747 | B7: Volumes | C7: Oil Volume (MBBLs) | D7: =SE!G3 -> 74883.63
A8: =SE!H$1 -> 45777 | B8: Volumes | C8: Oil Volume (MBBLs) | D8: =SE!H3 -> 74829.498
A9: =SE!I$1 -> 45808 | B9: Volumes | C9: Oil Volume (MBBLs) | D9: =SE!I3 -> 76786.121
A10: =SE!J$1 -> 45838 | B10: Volumes | C10: Oil Volume (MBBLs) | D10: =SE!J3 -> 78039.753
A11: =SE!K$1 -> 45869 | B11: Volumes | C11: Oil Volume (MBBLs) | D11: =SE!K3 -> 69919.451
A12: =SE!L$1 -> 45900 | B12: Volumes | C12: Oil Volume (MBBLs) | D12: =SE!L3 -> 71142.207
A13: =SE!M$1 -> 45930 | B13: Volumes | C13: Oil Volume (MBBLs) | D13: =SE!M3 -> 76706.797
A14: =SE!B$1 -> 45596 | B14: Volumes | C14: Gas Volume (MMCF) | D14: =SE!B4 -> 0
A15: =SE!C$1 -> 45626 | B15: Volumes | C15: Gas Volume (MMCF) | D15: =SE!C4 -> 0
A16: =SE!D$1 -> 45657 | B16: Volumes | C16: Gas Volume (MMCF) | D16: =SE!D4 -> 0
A17: =SE!E$1 -> 45688 | B17: Volumes | C17: Gas Volume (MMCF) | D17: =SE!E4 -> 0
A18: =SE!F$1 -> 45716 | B18: Volumes | C18: Gas Volume (MMCF) | D18: =SE!F4 -> 0
A19: =SE!G$1 -> 45747 | B19: Volumes | C19: Gas Volume (MMCF) | D19: =SE!G4 -> 0
A20: =SE!H$1 -> 45777 | B20: Volumes | C20: Gas Volume (MMCF) | D20: =SE!H4 -> 0
A21: =SE!I$1 -> 45808 | B21: Volumes | C21: Gas Volume (MMCF) | D21: =SE!I4 -> 0
A22: =SE!J$1 -> 45838 | B22: Volumes | C22: Gas Volume (MMCF) | D22: =SE!J4 -> 0
A23: =SE!K$1 -> 45869 | B23: Volumes | C23: Gas Volume (MMCF) | D23: =SE!K4 -> 0
A24: =SE!L$1 -> 45900 | B24: Volumes | C24: Gas Volume (MMCF) | D24: =SE!L4 -> 0
A25: =SE!M$1 -> 45930 | B25: Volumes | C25: Gas Volume (MMCF) | D25: =SE!M4 -> 0
A26: =SE!B$1 -> 45596 | B26: Volumes | C26: NGL Volume (MBBLs) | D26: =SE!B5 -> 9207.996
A27: =SE!C$1 -> 45626 | B27: Volumes | C27: NGL Volume (MBBLs) | D27: =SE!C5 -> 8723.234
A28: =SE!D$1 -> 45657 | B28: Volumes | C28: NGL Volume (MBBLs) | D28: =SE!D5 -> 8649.823
A29: =SE!E$1 -> 45688 | B29: Volumes | C29: NGL Volume (MBBLs) | D29: =SE!E5 -> 7846.271
A30: =SE!F$1 -> 45716 | B30: Volumes | C30: NGL Volume (MBBLs) | D30: =SE!F5 -> 6166.18
A31: =SE!G$1 -> 45747 | B31: Volumes | C31: NGL Volume (MBBLs) | D31: =SE!G5 -> 8340.917
A32: =SE!H$1 -> 45777 | B32: Volumes | C32: NGL Volume (MBBLs) | D32: =SE!H5 -> 8759.578
A33: =SE!I$1 -> 45808 | B33: Volumes | C33: NGL Volume (MBBLs) | D33: =SE!I5 -> 6530.336
A34: =SE!J$1 -> 45838 | B34: Volumes | C34: NGL Volume (MBBLs) | D34: =SE!J5 -> 11455.54
A35: =SE!K$1 -> 45869 | B35: Volumes | C35: NGL Volume (MBBLs) | D35: =SE!K5 -> 2682.949
A36: =SE!L$1 -> 45900 | B36: Volumes | C36: NGL Volume (MBBLs) | D36: =SE!L5 -> 9555.773
A37: =SE!M$1 -> 45930 | B37: Volumes | C37: NGL Volume (MBBLs) | D37: =SE!M5 -> 9242.44
A38: =SE!B$1 -> 45596 | B38: Volumes | C38: Total (MBoe) | D38: =SE!B6 -> 81561.844
A39: =SE!C$1 -> 45626 | B39: Volumes | C39: Total (MBoe) | D39: =SE!C6 -> 79225.712
A40: =SE!D$1 -> 45657 | B40: Volumes | C40: Total (MBoe) | D40: =SE!D6 -> 84941.604
A41: =SE!E$1 -> 45688 | B41: Volumes | C41: Total (MBoe) | D41: =SE!E6 -> 78798.372
A42: =SE!F$1 -> 45716 | B42: Volumes | C42: Total (MBoe) | D42: =SE!F6 -> 68828.263
A43: =SE!G$1 -> 45747 | B43: Volumes | C43: Total (MBoe) | D43: =SE!G6 -> 83224.547
A44: =SE!H$1 -> 45777 | B44: Volumes | C44: Total (MBoe) | D44: =SE!H6 -> 83589.076
A45: =SE!I$1 -> 45808 | B45: Volumes | C45: Total (MBoe) | D45: =SE!I6 -> 83316.457
A46: =SE!J$1 -> 45838 | B46: Volumes | C46: Total (MBoe) | D46: =SE!J6 -> 89495.293
A47: =SE!K$1 -> 45869 | B47: Volumes | C47: Total (MBoe) | D47: =SE!K6 -> 72602.4
A48: =SE!L$1 -> 45900 | B48: Volumes | C48: Total (MBoe) | D48: =SE!L6 -> 80697.98
A49: =SE!M$1 -> 45930 | B49: Volumes | C49: Total (MBoe) | D49: =SE!M6 -> 85949.237
A50: =SE!B$1 -> 45596 | B50: Volumes | C50: Total (MBoe/d) | D50: =SE!B7 -> 0
A51: =SE!C$1 -> 45626 | B51: Volumes | C51: Total (MBoe/d) | D51: =SE!C7 -> 0
A52: =SE!D$1 -> 45657 | B52: Volumes | C52: Total (MBoe/d) | D52: =SE!D7 -> 0
A53: =SE!E$1 -> 45688 | B53: Volumes | C53: Total (MBoe/d) | D53: =SE!E7 -> 0
A54: =SE!F$1 -> 45716 | B54: Volumes | C54: Total (MBoe/d) | D54: =SE!F7 -> 0
A55: =SE!G$1 -> 45747 | B55: Volumes | C55: Total (MBoe/d) | D55: =SE!G7 -> 0
A56: =SE!H$1 -> 45777 | B56: Volumes | C56: Total (MBoe/d) | D56: =SE!H7 -> 0
A57: =SE!I$1 -> 45808 | B57: Volumes | C57: Total (MBoe/d) | D57: =SE!I7 -> 0
A58: =SE!J$1 -> 45838 | B58: Volumes | C58: Total (MBoe/d) | D58: =SE!J7 -> 0
A59: =SE!K$1 -> 45869 | B59: Volumes | C59: Total (MBoe/d) | D59: =SE!K7 -> 0
A60: =SE!L$1 -> 45900 | B60: Volumes | C60: Total (MBoe/d) | D60: =SE!L7 -> 0
A61: =SE!M$1 -> 45930 | B61: Volumes | C61: Total (MBoe/d) | D61: =SE!M7 -> 0
A62: =SE!B$1 -> 45596 | B62: Revenue | C62: Oil Revenue | D62: =SE!B9 -> 4554938.1
A63: =SE!C$1 -> 45626 | B63: Revenue | C63: Oil Revenue | D63: =SE!C9 -> 4410882.8
A64: =SE!D$1 -> 45657 | B64: Revenue | C64: Oil Revenue | D64: =SE!D9 -> 4784355.5
A65: =SE!E$1 -> 45688 | B65: Revenue | C65: Oil Revenue | D65: =SE!E9 -> 4808684.2
A66: =SE!F$1 -> 45716 | B66: Revenue | C66: Oil Revenue | D66: =SE!F9 -> 4010354.5
A67: =SE!G$1 -> 45747 | B67: Revenue | C67: Oil Revenue | D67: =SE!G9 -> 4443915.3
A68: =SE!H$1 -> 45777 | B68: Revenue | C68: Oil Revenue | D68: =SE!H9 -> 4169707.1
A69: =SE!I$1 -> 45808 | B69: Revenue | C69: Oil Revenue | D69: =SE!I9 -> 4335379.9
A70: =SE!J$1 -> 45838 | B70: Revenue | C70: Oil Revenue | D70: =SE!J9 -> 4928770.3
A71: =SE!K$1 -> 45869 | B71: Revenue | C71: Oil Revenue | D71: =SE!K9 -> 4424675
A72: =SE!L$1 -> 45900 | B72: Revenue | C72: Oil Revenue | D72: =SE!L9 -> 4171704.3
A73: =SE!M$1 -> 45930 | B73: Revenue | C73: Oil Revenue | D73: =SE!M9 -> 4342062.5
A74: =SE!B$1 -> 45596 | B74: Revenue | C74: Gas Revenue | D74: =SE!B10 -> 0
A75: =SE!C$1 -> 45626 | B75: Revenue | C75: Gas Revenue | D75: =SE!C10 -> 0
A76: =SE!D$1 -> 45657 | B76: Revenue | C76: Gas Revenue | D76: =SE!D10 -> 0
A77: =SE!E$1 -> 45688 | B77: Revenue | C77: Gas Revenue | D77: =SE!E10 -> 0
A78: =SE!F$1 -> 45716 | B78: Revenue | C78: Gas Revenue | D78: =SE!F10 -> 0
A79: =SE!G$1 -> 45747 | B79: Revenue | C79: Gas Revenue | D79: =SE!G10 -> 0
A80: =SE!H$1 -> 45777 | B80: Revenue | C80: Gas Revenue | D80: =SE!H10 -> 0
A81: =SE!I$1 -> 45808 | B81: Revenue | C81: Gas Revenue | D81: =SE!I10 -> 0
A82: =SE!J$1 -> 45838 | B82: Revenue | C82: Gas Revenue | D82: =SE!J10 -> 0
A83: =SE!K$1 -> 45869 | B83: Revenue | C83: Gas Revenue | D83: =SE!K10 -> 0
A84: =SE!L$1 -> 45900 | B84: Revenue | C84: Gas Revenue | D84: =SE!L10 -> 0
A85: =SE!M$1 -> 45930 | B85: Revenue | C85: Gas Revenue | D85: =SE!M10 -> 0
A86: =SE!B$1 -> 45596 | B86: Revenue | C86: NGL Revenue | D86: =SE!B11 -> 506236.61
A87: =SE!C$1 -> 45626 | B87: Revenue | C87: NGL Revenue | D87: =SE!C11 -> 486197.25
A88: =SE!D$1 -> 45657 | B88: Revenue | C88: NGL Revenue | D88: =SE!D11 -> 466767.59
A89: =SE!E$1 -> 45688 | B89: Revenue | C89: NGL Revenue | D89: =SE!E11 -> 453514.62
A90: =SE!F$1 -> 45716 | B90: Revenue | C90: NGL Revenue | D90: =SE!F11 -> 329502.51
A91: =SE!G$1 -> 45747 | B91: Revenue | C91: NGL Revenue | D91: =SE!G11 -> 431592.81
A92: =SE!H$1 -> 45777 | B92: Revenue | C92: NGL Revenue | D92: =SE!H11 -> 423339.83
A93: =SE!I$1 -> 45808 | B93: Revenue | C93: NGL Revenue | D93: =SE!I11 -> 314637.75
A94: =SE!J$1 -> 45838 | B94: Revenue | C94: NGL Revenue | D94: =SE!J11 -> 543535.02
A95: =SE!K$1 -> 45869 | B95: Revenue | C95: NGL Revenue | D95: =SE!K11 -> 121273.23
A96: =SE!L$1 -> 45900 | B96: Revenue | C96: NGL Revenue | D96: =SE!L11 -> 456105.65
A97: =SE!M$1 -> 45930 | B97: Revenue | C97: NGL Revenue | D97: =SE!M11 -> 438200.52
A98: =SE!B$1 -> 45596 | B98: Revenue | C98: Sulfur Revenue | D98: =SE!B12 -> 9309.16
A99: =SE!C$1 -> 45626 | B99: Revenue | C99: Sulfur Revenue | D99: =SE!C12 -> 6987.7
A100: =SE!D$1 -> 45657 | B100: Revenue | C100: Sulfur Revenue | D100: =SE!D12 -> 7014.08
...
